norwegianblue/__init__.py
norwegianblue/__main__.py
norwegianblue/_cache.py
norwegianblue/_data.py
norwegianblue/_version.py
norwegianblue/cli.py
norwegianblue-0.24.1.dist-info/METADATA
norwegianblue-0.24.1.dist-info/WHEEL
norwegianblue-0.24.1.dist-info/entry_points.txt
norwegianblue-0.24.1.dist-info/licenses/LICENSE.txt
norwegianblue-0.24.1.dist-info/RECORD
