Metadata-Version: 2.4
Name: norwegianblue
Version: 0.24.1
Summary: CLI to show end-of-life dates for a number of products
Project-URL: Changelog, https://github.com/hugovk/norwegianblue/releases
Project-URL: Homepage, https://github.com/hugovk/norwegianblue
Project-URL: Source, https://github.com/hugovk/norwegianblue
Author: Hugo van Kemenade
License-Expression: MIT
License-File: LICENSE.txt
Keywords: cli,end-of-life,endoflife,eol
Classifier: Development Status :: 3 - Alpha
Classifier: Intended Audience :: Developers
Classifier: Intended Audience :: End Users/Desktop
Classifier: Operating System :: OS Independent
Classifier: Programming Language :: Python :: 3 :: Only
Classifier: Programming Language :: Python :: 3.10
Classifier: Programming Language :: Python :: 3.11
Classifier: Programming Language :: Python :: 3.12
Classifier: Programming Language :: Python :: 3.13
Classifier: Programming Language :: Python :: 3.14
Classifier: Programming Language :: Python :: 3.15
Classifier: Programming Language :: Python :: Implementation :: CPython
Classifier: Programming Language :: Python :: Implementation :: PyPy
Requires-Python: >=3.10
Requires-Dist: argcomplete>=3.4; platform_system != 'Windows'
Requires-Dist: platformdirs
Requires-Dist: prettytable>=3.16
Requires-Dist: pytablewriter[html]>=0.63
Requires-Dist: python-slugify
Requires-Dist: termcolor>=2.1
Requires-Dist: urllib3>=2
Requires-Dist: yaspin
Provides-Extra: tests
Requires-Dist: freezegun; extra == 'tests'
Requires-Dist: pytest; extra == 'tests'
Requires-Dist: pytest-cov; extra == 'tests'
Requires-Dist: termcolor>=3.2; extra == 'tests'
